prawtools/__init__.py
prawtools/alert.py
prawtools/helpers.py
prawtools/mod.py
prawtools/stats.py
prawtools-1.0.0.dist-info/LICENSE.txt
prawtools-1.0.0.dist-info/METADATA
prawtools-1.0.0.dist-info/WHEEL
prawtools-1.0.0.dist-info/entry_points.txt
prawtools-1.0.0.dist-info/top_level.txt
prawtools-1.0.0.dist-info/RECORD
