Metadata-Version: 2.1
Name: prawtools
Version: 1.0.0
Summary: A collection of utilities that utilize the reddit API.
Home-page: https://github.com/praw-dev/prawtools
Author: Bryce Boe
Author-email: bbzbryce@gmail.com
License: Simplified BSD License
Keywords: reddit mod moderator subreddit statistics tools
Platform: UNKNOWN
Classifier: Environment :: Console
Classifier: Intended Audience :: Developers
Classifier: License :: OSI Approved :: BSD License
Classifier: Natural Language :: English
Classifier: Operating System :: OS Independent
Classifier: Programming Language :: Python :: 2.7
Classifier: Programming Language :: Python :: 3
Classifier: Programming Language :: Python :: 3.4
Classifier: Programming Language :: Python :: 3.5
Classifier: Programming Language :: Python :: 3.6
Classifier: Topic :: Utilities
Requires-Dist: praw (<7,>=4.0.0)
Requires-Dist: six (<2,>=1)
